depsgraph/__init__.py
python_module_deps-0.1.0.dist-info/METADATA
python_module_deps-0.1.0.dist-info/WHEEL
python_module_deps-0.1.0.dist-info/top_level.txt
python_module_deps-0.1.0.dist-info/RECORD
