Metadata-Version: 2.4
Name: python-module-deps
Version: 0.1.0
Summary: Add your description here
Requires-Python: >=3.13
Requires-Dist: build>=1.4.0
